icepool/__init__.py
icepool/creation_args.py
icepool/expand.py
icepool/function.py
icepool/lexi.py
icepool/math.py
icepool/order.py
icepool/typing.py
icepool/wallenius.py
icepool/collection/__init__.py
icepool/collection/counts.py
icepool/collection/symbols.py
icepool/collection/vector.py
icepool/collection/vector_with_truth_only.py
icepool/evaluator/__init__.py
icepool/evaluator/argsort.py
icepool/evaluator/basic.py
icepool/evaluator/comparison.py
icepool/evaluator/keep.py
icepool/evaluator/lexi.py
icepool/evaluator/multiset_evaluator.py
icepool/evaluator/multiset_evaluator_base.py
icepool/evaluator/multiset_function.py
icepool/evaluator/poker.py
icepool/expression/__init__.py
icepool/expression/multiset_expression.py
icepool/expression/multiset_expression_base.py
icepool/expression/multiset_mixture.py
icepool/expression/multiset_parameter.py
icepool/expression/multiset_tuple_expression.py
icepool/generator/__init__.py
icepool/generator/compound_keep.py
icepool/generator/deal.py
icepool/generator/keep.py
icepool/generator/multi_deal.py
icepool/generator/multiset_generator.py
icepool/generator/multiset_tuple_generator.py
icepool/generator/pool.py
icepool/generator/weightless.py
icepool/map_tools/__init__.py
icepool/map_tools/common.py
icepool/map_tools/core_impl.py
icepool/map_tools/function.py
icepool/map_tools/markov_chain.py
icepool/operator/__init__.py
icepool/operator/adjust_counts.py
icepool/operator/binary.py
icepool/operator/debug.py
icepool/operator/filter_outcomes.py
icepool/operator/keep.py
icepool/operator/multiset_operator.py
icepool/operator/pair.py
icepool/operator/versus.py
icepool/population/__init__.py
icepool/population/again.py
icepool/population/base.py
icepool/population/deck.py
icepool/population/die.py
icepool/population/die_with_truth.py
icepool/population/format.py
icepool/population/keep.py
icepool-2.2.1.dist-info/licenses/LICENSE.md
icepool-2.2.1.dist-info/METADATA
icepool-2.2.1.dist-info/WHEEL
icepool-2.2.1.dist-info/top_level.txt
icepool-2.2.1.dist-info/RECORD
