Metadata-Version: 2.4
Name: icepool
Version: 2.2.1
Summary: Dice probability package.
Home-page: https://github.com/HighDiceRoller/icepool
Author: Albert Julius Liu
Author-email: ajul1987+highdiceroller@gmail.com
Project-URL: Twitter, https://twitter.com/highdiceroller
Classifier: Development Status :: 5 - Production/Stable
Classifier: License :: OSI Approved :: MIT License
Classifier: Programming Language :: Python :: 3
Classifier: Programming Language :: Python :: 3.12
Classifier: Topic :: Games/Entertainment :: Board Games
Classifier: Topic :: Games/Entertainment :: Role-Playing
Classifier: Topic :: Scientific/Engineering :: Mathematics
Classifier: Typing :: Typed
Requires-Python: >=3.12
License-File: LICENSE.md
Dynamic: license-file
